torchcrepe/__init__.py
torchcrepe/__main__.py
torchcrepe/convert.py
torchcrepe/core.py
torchcrepe/decode.py
torchcrepe/filter.py
torchcrepe/load.py
torchcrepe/loudness.py
torchcrepe/model.py
torchcrepe/threshold.py
torchcrepe/assets/full.pth
torchcrepe/assets/tiny.pth
torchcrepe-0.0.24.dist-info/licenses/LICENSE
torchcrepe-0.0.24.dist-info/METADATA
torchcrepe-0.0.24.dist-info/WHEEL
torchcrepe-0.0.24.dist-info/top_level.txt
torchcrepe-0.0.24.dist-info/RECORD
