Metadata-Version: 2.4
Name: torchcrepe
Version: 0.0.24
Summary: Pytorch implementation of CREPE pitch tracker
Home-page: https://github.com/maxrmorrison/torchcrepe
Author: Max Morrison
Author-email: maxrmorrison@gmail.com
License: MIT
Keywords: pitch,audio,speech,music,pytorch,crepe
Classifier: License :: OSI Approved :: MIT License
License-File: LICENSE
Requires-Dist: librosa>=0.9.1
Requires-Dist: resampy
Requires-Dist: scipy
Requires-Dist: torch
Requires-Dist: torchaudio
Requires-Dist: tqdm
Dynamic: author
Dynamic: author-email
Dynamic: classifier
Dynamic: description
Dynamic: description-content-type
Dynamic: home-page
Dynamic: keywords
Dynamic: license
Dynamic: license-file
Dynamic: requires-dist
Dynamic: summary
